Memory_Moduling/pipe_ex.v
module pipe_ex(F,A,B,C,D,clk);
parameter N=100;
input [N-1:0] A,B,C,D;
input clk;
output [N-1:0] F;
reg [N-1:0] L12_X1,L12_X2,L12_D,L23_X3,L23_D,L34_F;
assign F=L34_F;
always@(posedge clk) //STAGE1
begin
L12_X1 <= #4 A+B;
L12_X2 <= #4 C-D;
L12_D <= D;
end
always@(posedge clk) //STAGE2
begin
L23_X3 <= #4 L12_X1 + L12_X2;
L23_D <= L12_D;
end
always@(posedge clk) //STAGE3
begin
L34_F=L23_X3*L23_D;
end
endmodule

Memory_Moduling/pipel_test.v
module pipel_test;
parameter N=100;
wire [N-1:0] F;
reg [N-1:0] A,B,C,D;
reg clk;
pipe_ex MYPIPE (F,A,B,C,D,clk);
initial clk=0;
always #10 clk = ~clk;
initial 
begin
#5 A=10; B=12; C=6; D=3; //F=75
#20 A=10; B=10; C=5; D=3; //F=66
#20 A=20; B=11; C=1; D=4; //F=112
end
initial 
begin
$dumpfile("pipel.vcd");
$dumpvars(0,pipel_test);
$monitor ("Time: %d,F=%d", $time,F);
#300 $finish;
end
endmodule

Memory_Moduling/pipel.vcd
$date
    Apr  4, 2022  15:29:32
$end
$version
    TOOL:	ncsim(64)	15.20-s051
$end
$timescale
    1 ns
$end

$scope module pipel_test $end
$var parameter 32 !    N  $end
$var wire     100 "    F [99:0] $end
$var reg      100 #    A [99:0] $end
$var reg      100 $    B [99:0] $end
$var reg      100 %    C [99:0] $end
$var reg      100 &    D [99:0] $end
$var reg       1 '    clk  $end

$scope module MYPIPE $end
$var parameter 32 (    N  $end
$var wire     100 )    A [99:0] $end
$var wire     100 *    B [99:0] $end
$var wire     100 +    C [99:0] $end
$var wire     100 ,    D [99:0] $end
$var wire      1 -    clk  $end
$var wire     100 "    F [99:0] $end
$var reg      100 .    L12_X1 [99:0] $end
$var reg      100 /    L12_X2 [99:0] $end
$var reg      100 0    L12_D [99:0] $end
$var reg      100 1    L23_X3 [99:0] $end
$var reg      100 2    L23_D [99:0] $end
$var reg      100 3    L34_F [99:0] $end
$upscope $end

$upscope $end

$enddefinitions $end
$dumpvars
b1100100 (
b1100100 !
bx "
bx #
bx $
bx %
bx &
0'
bx )
bx *
bx +
bx ,
0-
bx .
bx /
bx 0
bx 1
bx 2
bx 3
$end
#5
b1010 #
b1100 $
b110 %
b11 &
b11 ,
b110 +
b1100 *
b1010 )
#10
1'
1-
b11 0
#14
b10110 .
b11 /
#20
0'
0-
#25
b1010 $
b101 %
b101 +
b1010 *
#30
1'
1-
b11 2
#34
b11001 1
b10100 .
b10 /
#40
0'
0-
#45
b10100 #
b1011 $
b1 %
b100 &
b100 ,
b1 +
b1011 *
b10100 )
#50
1'
1-
b1001011 3
b1001011 "
b100 0
#54
b10110 1
b11111 .
b1111111111111111111111111111111111111111111111111111111111111111111111111111111111111111111111111101 /
#60
0'
0-
#70
1'
1-
b1000010 3
b1000010 "
b100 2
#74
b11100 1
#80
0'
0-
#90
1'
1-
b1110000 3
b1110000 "
